{
  "_generic": {
    "defaultPackage": "main",
    "invalidationHash": "e3d68754d9c534c46758a4d0ae2f8c860e0aeb401291497ef96cbb58cbcbe1a1",
    "location": "",
    "packages": {
      "main": ""
    },
    "sourcesAggregatedHash": null,
    "subsystem": "python"
  },
  "_subsystem": {
    "application": false,
    "pythonAttr": "python310",
    "sourceFormats": {
      "PyMySQL": "wheel",
      "certifi": "wheel",
      "charset_normalizer": "wheel",
      "contextlib2": "wheel",
      "docopt": "sdist",
      "file_read_backwards": "wheel",
      "idna": "wheel",
      "internetarchive": "sdist",
      "jsonpatch": "wheel",
      "jsonpointer": "wheel",
      "lxml": "wheel",
      "mwclient": "wheel",
      "oauthlib": "wheel",
      "poetry_core": "wheel",
      "poster3": "wheel",
      "pre_commit_poetry_export": "wheel",
      "pywikibot": "sdist",
      "requests": "wheel",
      "requests_oauthlib": "wheel",
      "schema": "wheel",
      "setuptools": "wheel",
      "six": "wheel",
      "tqdm": "wheel",
      "urllib3": "wheel",
      "wikitools3": "wheel"
    }
  },
  "sources": {
    "PyMySQL": {
      "1.0.2": {
        "hash": "sha256-Qfw6DFAT1fA5Y5RCMhGFUy4+LIkkaHq+ZTfeFX1ANkE=",
        "type": "http",
        "url": "https://files.pythonhosted.org/packages/py3/P/PyMySQL/PyMySQL-1.0.2-py3-none-any.whl"
      }
    },
    "certifi": {
      "2022.12.7": {
        "hash": "sha256-StMjL16SbWcY7DHPwfyt/eAgkg4nhoQURVHJF2nHvBg=",
        "type": "http",
        "url": "https://files.pythonhosted.org/packages/py3/c/certifi/certifi-2022.12.7-py3-none-any.whl"
      }
    },
    "charset_normalizer": {
      "2.1.1": {
        "hash": "sha256-g+mnXRkRJ5r9iTUsaLRTSFWdH8BQawVLNGZRtef+4p8=",
        "type": "http",
        "url": "https://files.pythonhosted.org/packages/py3/c/charset_normalizer/charset_normalizer-2.1.1-py3-none-any.whl"
      }
    },
    "contextlib2": {
      "21.6.0": {
        "hash": "sha256-P722RGav0jq69sl3Ynt1thOaWj6M44QFxbQTrtegRx8=",
        "type": "http",
        "url": "https://files.pythonhosted.org/packages/py2.py3/c/contextlib2/contextlib2-21.6.0-py2.py3-none-any.whl"
      }
    },
    "docopt": {
      "-": {
        "hash": "sha256-SbOoJSgL1ms6qDWF71nEqMgvLIpSLb51SovI0IyFxJE=",
        "type": "http",
        "url": "https://files.pythonhosted.org/packages/source/d/docopt/docopt-0.6.2.tar.gz"
      }
    },
    "file_read_backwards": {
      "2.0.0": {
        "hash": "sha256-eGhKr8BHHp4PYqhmI2G/r3Ct49ODM9fxZv2AJKAosdE=",
        "type": "http",
        "url": "https://files.pythonhosted.org/packages/py2.py3/f/file_read_backwards/file_read_backwards-2.0.0-py2.py3-none-any.whl"
      }
    },
    "idna": {
      "3.4": {
        "hash": "sha256-kLd+eeqj66begZoMRCwLTO78NBp6Krd9dWK/SfQlxcI=",
        "type": "http",
        "url": "https://files.pythonhosted.org/packages/py3/i/idna/idna-3.4-py3-none-any.whl"
      }
    },
    "internetarchive": {
      "-": {
        "hash": "sha256-+oncS+PgoK7iSBCkp1TiSt/Qft9xDGRbT2QkIsYHi40=",
        "type": "http",
        "url": "https://files.pythonhosted.org/packages/source/i/internetarchive/internetarchive-2.3.0.tar.gz"
      }
    },
    "jsonpatch": {
      "1.32": {
        "hash": "sha256-Jqw4Vxmsn1Tfii8IJ7uCU6o+qKt7M2hFe824wUWVo5c=",
        "type": "http",
        "url": "https://files.pythonhosted.org/packages/py2.py3/j/jsonpatch/jsonpatch-1.32-py2.py3-none-any.whl"
      }
    },
    "jsonpointer": {
      "2.3": {
        "hash": "sha256-UYAeVYU5tOnNJoY4wHjGxXRsmslrw4FS1ENADk83k+k=",
        "type": "http",
        "url": "https://files.pythonhosted.org/packages/py2.py3/j/jsonpointer/jsonpointer-2.3-py2.py3-none-any.whl"
      }
    },
    "lxml": {
      "4.9.2": {
        "hash": "sha256-Grjx+TLo+CNV513aVBOldhLG6kSAadT7LiF+mkvtE9Q=",
        "type": "http",
        "url": "https://files.pythonhosted.org/packages/cp310/l/lxml/lxml-4.9.2-cp310-cp310-manylinux_2_17_x86_64.manylinux2014_x86_64.manylinux_2_24_x86_64.whl"
      }
    },
    "mwclient": {
      "0.10.1": {
        "hash": "sha256-eq0ADEx/I5x8ksQ+LV+9r4VzJirM1gcFJP9C5GlQMG4=",
        "type": "http",
        "url": "https://files.pythonhosted.org/packages/py2.py3/m/mwclient/mwclient-0.10.1-py2.py3-none-any.whl"
      }
    },
    "oauthlib": {
      "3.2.2": {
        "hash": "sha256-gTnymqwT4l1QJoDp4Zlj6D8Wg41IoNccKH/kDnBn+8o=",
        "type": "http",
        "url": "https://files.pythonhosted.org/packages/py3/o/oauthlib/oauthlib-3.2.2-py3-none-any.whl"
      }
    },
    "poetry_core": {
      "1.4.0": {
        "hash": "sha256-VVmrgDhKwCHbMp7zFwhkF+FA7hF2vPyzo4OLVE4hPI4=",
        "type": "http",
        "url": "https://files.pythonhosted.org/packages/py3/p/poetry_core/poetry_core-1.4.0-py3-none-any.whl"
      }
    },
    "poster3": {
      "0.8.1": {
        "hash": "sha256-GyfX1j4xkeXXI4Yx/IKORJNZDpTc6gNOOGwHnYU8zhQ=",
        "type": "http",
        "url": "https://files.pythonhosted.org/packages/py3/p/poster3/poster3-0.8.1-py3-none-any.whl"
      }
    },
    "pre_commit_poetry_export": {
      "0.1.2": {
        "hash": "sha256-S9xSF/SSCDkR/mr+R6NTKyqzQQjtbNfhWbYDhR97A1c=",
        "type": "http",
        "url": "https://files.pythonhosted.org/packages/py3/p/pre_commit_poetry_export/pre_commit_poetry_export-0.1.2-py3-none-any.whl"
      }
    },
    "pywikibot": {
      "-": {
        "hash": "sha256-csL8RhXeC3sKFYrFQHMX7T3Z0SUNNxKBzBhnLp0POE0=",
        "type": "http",
        "url": "https://files.pythonhosted.org/packages/source/p/pywikibot/pywikibot-6.6.5.tar.gz"
      }
    },
    "requests": {
      "2.28.1": {
        "hash": "sha256-j++ioaE2W/VSCqxBg2++5HnaZ4ZFFL24IfMc4HzmU0k=",
        "type": "http",
        "url": "https://files.pythonhosted.org/packages/py3/r/requests/requests-2.28.1-py3-none-any.whl"
      }
    },
    "requests_oauthlib": {
      "1.3.1": {
        "hash": "sha256-JXfFAaL7jQWjBMCdCQ1uR8MG/vFYCdECsyfPg2S92rU=",
        "type": "http",
        "url": "https://files.pythonhosted.org/packages/py2.py3/r/requests_oauthlib/requests_oauthlib-1.3.1-py2.py3-none-any.whl"
      }
    },
    "schema": {
      "0.7.5": {
        "hash": "sha256-8//e6toJ7DS/QNfXmZbZ9xdduTt6UGXeD6p/QQg8Hmw=",
        "type": "http",
        "url": "https://files.pythonhosted.org/packages/py2.py3/s/schema/schema-0.7.5-py2.py3-none-any.whl"
      }
    },
    "setuptools": {
      "65.7.0": {
        "hash": "sha256-irTx2/K0pl9+7FrQxiDoTDQRGmjTNJgzSUuQiCEiFN0=",
        "type": "http",
        "url": "https://files.pythonhosted.org/packages/py3/s/setuptools/setuptools-65.7.0-py3-none-any.whl"
      }
    },
    "six": {
      "1.16.0": {
        "hash": "sha256-irsvHYaJCi37mJ+ad8/P0+R8KjVLAREXcTJviqJuAlQ=",
        "type": "http",
        "url": "https://files.pythonhosted.org/packages/py2.py3/s/six/six-1.16.0-py2.py3-none-any.whl"
      }
    },
    "tqdm": {
      "4.64.1": {
        "hash": "sha256-b+4WDW/80bHGjGXxTIKcIoMrxAFyYzXOksUtOVlEpqE=",
        "type": "http",
        "url": "https://files.pythonhosted.org/packages/py2.py3/t/tqdm/tqdm-4.64.1-py2.py3-none-any.whl"
      }
    },
    "urllib3": {
      "1.26.14": {
        "hash": "sha256-de3NwvfYWxNxJKbDyfw5M83qoS7LmmqVnyJ5eg/sp+E=",
        "type": "http",
        "url": "https://files.pythonhosted.org/packages/py2.py3/u/urllib3/urllib3-1.26.14-py2.py3-none-any.whl"
      }
    },
    "wikitools3": {
      "3.0.1": {
        "hash": "sha256-qxoT2b6DHrEYbPDyuKxIfd4JMtrYLGxgMfKPpBWED+Q=",
        "type": "http",
        "url": "https://files.pythonhosted.org/packages/py3/w/wikitools3/wikitools3-3.0.1-py3-none-any.whl"
      }
    }
  }
}
